rosoku/__init__.py
rosoku/conventional.py
rosoku/deeplearning.py
rosoku/attribution/__init__.py
rosoku/attribution/saliency_map.py
rosoku/preprocessing/__init__.py
rosoku/preprocessing/normalization.py
rosoku/tl/__init__.py
rosoku/tl/alignment.py
rosoku/utils/__init__.py
rosoku/utils/core.py
rosoku/utils/data_load.py
rosoku/viz/__init__.py
rosoku/viz/core.py
rosoku-0.0.7.dist-info/licenses/LICENSE
rosoku-0.0.7.dist-info/METADATA
rosoku-0.0.7.dist-info/WHEEL
rosoku-0.0.7.dist-info/top_level.txt
rosoku-0.0.7.dist-info/RECORD
