Metadata-Version: 2.4
Name: rosoku
Version: 0.0.7
Summary: A flexible callback-based toolkit for EEG/BCI experiments that lets you define data loading and preprocessing freely, while rosoku handles training, evaluation, and result logging for conventional and deep-learning models.
Author: Simon Kojima, Alex Pepi
License: BSD 3-Clause License
Requires-Python: >=3.11
License-File: LICENSE
Requires-Dist: numpy
Requires-Dist: scipy
Requires-Dist: pandas
Requires-Dist: mne
Requires-Dist: pyriemann
Requires-Dist: scikit-learn
Requires-Dist: torch
Requires-Dist: msgpack
Requires-Dist: pyarrow
Dynamic: license-file
